scratchcloud/__init__.py
scratchcloud/client.py
scratchcloud/errors.py
scratchcloud/ext/__init__.py
scratchcloud/ext/api.py
scratchcloud/ext/codecs.py
scratchcloud/ext/utils.py
scratchcloud-1.2.3.dist-info/LICENSE
scratchcloud-1.2.3.dist-info/METADATA
scratchcloud-1.2.3.dist-info/WHEEL
scratchcloud-1.2.3.dist-info/top_level.txt
scratchcloud-1.2.3.dist-info/RECORD
