Metadata-Version: 2.1
Name: scratchcloud
Version: 1.2.3
Summary: An event-based asynchronous wrapper for scratch.mit.edu cloud variables.
Home-page: https://github.com/yuwex/scratchcloud
Author: yuwex
License: UNKNOWN
Platform: UNKNOWN
Classifier: Development Status :: 5 - Production/Stable
Classifier: License :: OSI Approved :: MIT License
Classifier: Intended Audience :: Education
Classifier: Natural Language :: English
Classifier: Operating System :: OS Independent
Classifier: Programming Language :: Python :: 3.10
Classifier: Topic :: Software Development :: Libraries
Requires-Python: >=3.10
License-File: LICENSE
Requires-Dist: aiohttp (>=3.8.0)
Requires-Dist: websockets (>=10.1)
Provides-Extra: docs
Requires-Dist: sphinx (==4.3.2) ; extra == 'docs'
Requires-Dist: sphinx-rtd-theme (==1.0.0) ; extra == 'docs'
